sideload_nu_0_bin_668d01dae41b4d34e40f4944/__init__.py
sideload_nu_0_bin_668d01dae41b4d34e40f4944/nu-0.95.0-x86_64-pc-windows-msvc.zip
sideload_nu_0_bin_668d01dae41b4d34e40f4944-1.0.0.dist-info/METADATA
sideload_nu_0_bin_668d01dae41b4d34e40f4944-1.0.0.dist-info/WHEEL
sideload_nu_0_bin_668d01dae41b4d34e40f4944-1.0.0.dist-info/top_level.txt
sideload_nu_0_bin_668d01dae41b4d34e40f4944-1.0.0.dist-info/RECORD
