Metadata-Version: 2.1
Name: sideload_nu_0_bin_668d01dae41b4d34e40f4944
Version: 1.0.0
Summary: Sideloaded package
Author: Null Void
Requires-Python: >=3.8
